RxjavaEssentialsZhongwenfanyiBan/README.md
RxjavaEssentialsZhongwenfanyiBan/__init__.py
RxjavaEssentialsZhongwenfanyiBan/__main__.py
RxjavaEssentialsZhongwenfanyiBan/file.epub
RxjavaEssentialsZhongwenfanyiBan/index.html
RxjavaEssentialsZhongwenfanyiBan/css/__init__.py
RxjavaEssentialsZhongwenfanyiBan/css/annotations.css
RxjavaEssentialsZhongwenfanyiBan/css/main.css
RxjavaEssentialsZhongwenfanyiBan/css/normalize.css
RxjavaEssentialsZhongwenfanyiBan/css/popup.css
RxjavaEssentialsZhongwenfanyiBan/font/__init__.py
RxjavaEssentialsZhongwenfanyiBan/font/fontello.eot
RxjavaEssentialsZhongwenfanyiBan/font/fontello.svg
RxjavaEssentialsZhongwenfanyiBan/font/fontello.ttf
RxjavaEssentialsZhongwenfanyiBan/font/fontello.woff
RxjavaEssentialsZhongwenfanyiBan/img/__init__.py
RxjavaEssentialsZhongwenfanyiBan/img/annotator-glyph-sprite.png
RxjavaEssentialsZhongwenfanyiBan/img/annotator-icon-sprite.png
RxjavaEssentialsZhongwenfanyiBan/img/apple-touch-icon.png
RxjavaEssentialsZhongwenfanyiBan/img/cancelfullscreen.png
RxjavaEssentialsZhongwenfanyiBan/img/close.png
RxjavaEssentialsZhongwenfanyiBan/img/fullscreen.png
RxjavaEssentialsZhongwenfanyiBan/img/loader.gif
RxjavaEssentialsZhongwenfanyiBan/img/menu-icon.png
RxjavaEssentialsZhongwenfanyiBan/img/save.png
RxjavaEssentialsZhongwenfanyiBan/img/saved.png
RxjavaEssentialsZhongwenfanyiBan/img/settings-s.png
RxjavaEssentialsZhongwenfanyiBan/img/settings.png
RxjavaEssentialsZhongwenfanyiBan/img/star.png
RxjavaEssentialsZhongwenfanyiBan/js/__init__.py
RxjavaEssentialsZhongwenfanyiBan/js/epub.js
RxjavaEssentialsZhongwenfanyiBan/js/epub.min.js
RxjavaEssentialsZhongwenfanyiBan/js/epub.min.map
RxjavaEssentialsZhongwenfanyiBan/js/hooks.min.js
RxjavaEssentialsZhongwenfanyiBan/js/hooks.min.map
RxjavaEssentialsZhongwenfanyiBan/js/reader.js
RxjavaEssentialsZhongwenfanyiBan/js/reader.js.map
RxjavaEssentialsZhongwenfanyiBan/js/reader.min.js
RxjavaEssentialsZhongwenfanyiBan/js/reader.min.map
RxjavaEssentialsZhongwenfanyiBan/js/hooks/__init__.py
rxjava_essentials_zhongwenfanyi_ban-2024.3.1.0.dist-info/METADATA
rxjava_essentials_zhongwenfanyi_ban-2024.3.1.0.dist-info/WHEEL
rxjava_essentials_zhongwenfanyi_ban-2024.3.1.0.dist-info/entry_points.txt
rxjava_essentials_zhongwenfanyi_ban-2024.3.1.0.dist-info/top_level.txt
rxjava_essentials_zhongwenfanyi_ban-2024.3.1.0.dist-info/RECORD
